Metadata-Version: 2.1
Name: postgres-table-as-queue-tools
Version: 0.0.2
Summary: There are just only several function to getting SQL queries for manage your table as a queue.
Home-page: https://github.com/vinger4/pg_table_as_queue_tools
Author: Evgenii Kozhanov
Author-email: evgenii.kozhanov@gmail.com
License: MIT
Platform: UNKNOWN
